calculadora_basica/__init__.py
calculadora_basica/calculadora.py
proy_calcu_nov_2024-0.1.0.dist-info/LICENSE
proy_calcu_nov_2024-0.1.0.dist-info/METADATA
proy_calcu_nov_2024-0.1.0.dist-info/WHEEL
proy_calcu_nov_2024-0.1.0.dist-info/top_level.txt
proy_calcu_nov_2024-0.1.0.dist-info/RECORD
