Metadata-Version: 2.1
Name: proy_calcu_nov_2024
Version: 0.1.0
Summary: Una calculadora básica con funciones simples
Home-page: https://github.com/tu_usuario/mi_calculadora_basica
Author: RASEC_2024
Author-email: csanchezc.sdigitales@gmail.com
Classifier: Programming Language :: Python :: 3
Classifier: License :: OSI Approved :: MIT License
Classifier: Operating System :: OS Independent
Requires-Python: >=3.6
License-File: LICENSE
Requires-Dist: setuptools
Requires-Dist: wheel
Requires-Dist: twine
